be_holder/__init__.py
be_holder/test_dec.py
be_holder/watcher.py
be_holder-1.2.dist-info/METADATA
be_holder-1.2.dist-info/WHEEL
be_holder-1.2.dist-info/top_level.txt
be_holder-1.2.dist-info/RECORD
