Metadata-Version: 2.1
Name: be-holder
Version: 1.2
Summary: A python module for type checking function parameters and returns
Home-page: https://github.com/wassafshahzad/beholder
Author: Wassaf Shahzad
Author-email: wassafshahzad@gmail.com
License: MIT
Platform: UNKNOWN
